{"stats":{"minecraft:dropped":{"minecraft:glow_berries":11,"minecraft:chest_minecart":2,"minecraft:gold_nugget":1,"minecraft:white_wool":3,"minecraft:dark_oak_door":3,"minecraft:stone_axe":4,"minecraft:cobbled_deepslate":5,"minecraft:rotten_flesh":2,"croptopia:saguaro_seed":3,"travelersbackpack:bat":2,"minecraft:white_bed":1,"appletreesrev:gold_apple_sapling":1,"minecraft:beetroot_seeds":4,"minecraft:melon_seeds":3,"minecraft:azalea":1,"minecraft:beef":1,"minecraft:glass":9,"minecraft:egg":1,"minecraft:feather":2,"minecraft:lead":2,"mcwfences:oak_pyramid_gate":3,"minecraft:stick":64,"minecraft:cobweb":13,"minecraft:diorite":9,"minecraft:wooden_hoe":1,"croptopia:sushi":3,"minecraft:torch":23,"minecraft:wooden_axe":3,"minecraft:stone_sword":3,"minecraft:shears":2,"minecraft:oak_boat":1,"minecraft:oak_sapling":3,"minecraft:wooden_shovel":1,"minecraft:red_sand":1,"minecraft:stone_pickaxe":5},"minecraft:custom":{"minecraft:animals_bred":1,"minecraft:interact_with_crafting_table":338,"minecraft:open_barrel":257,"minecraft:leave_game":19,"minecraft:time_since_death":278271,"minecraft:sprint_one_cm":292330,"minecraft:damage_blocked_by_shield":12265,"minecraft:drop":72,"minecraft:talked_to_villager":7,"minecraft:play_time":1523142,"minecraft:deaths":7,"minecraft:jump":6391,"minecraft:interact_with_brewingstand":2,"minecraft:walk_on_water_one_cm":47666,"minecraft:interact_with_furnace":131,"minecraft:interact_with_loom":8,"minecraft:sleep_in_bed":94,"minecraft:damage_dealt":23099,"minecraft:crouch_one_cm":63847,"minecraft:interact_with_smoker":27,"minecraft:horse_one_cm":32224,"minecraft:mob_kills":158,"minecraft:interact_with_campfire":3,"minecraft:climb_one_cm":103874,"minecraft:walk_one_cm":6509856,"minecraft:sneak_time":30431,"minecraft:walk_under_water_one_cm":41509,"minecraft:boat_one_cm":528822,"minecraft:interact_with_blast_furnace":19,"minecraft:total_world_time":1523142,"minecraft:raid_trigger":1,"minecraft:time_since_rest":5509,"minecraft:damage_taken":9518,"minecraft:swim_one_cm":28155,"minecraft:fly_one_cm":73108,"minecraft:pig_one_cm":797,"minecraft:open_chest":737,"minecraft:fish_caught":5,"minecraft:fall_one_cm":49903},"minecraft:broken":{"minecraft:golden_helmet":1,"minecraft:wooden_shovel":2,"minecraft:stone_pickaxe":16,"minecraft:stone_axe":1,"minecraft:wooden_axe":3,"minecraft:stone_shovel":2,"minecraft:stone_sword":4,"minecraft:wooden_pickaxe":2,"minecraft:shield":3,"minecraft:iron_pickaxe":1,"minecraft:wooden_hoe":3},"minecraft:picked_up":{"minecraft:wooden_axe":4,"minecraft:seagrass":14,"minecraft:wheat":27,"croptopia:shrimp":1,"travelersbackpack:bat":3,"croptopia:tomatillo_seed":3,"croptopia:broccoli":1,"minecraft:lead":6,"minecraft:oak_stairs":5,"croptopia:cinnamon_wood":1,"croptopia:calamari":1,"minecraft:string":24,"minecraft:raw_copper":31,"minecraft:pufferfish":2,"minecraft:oak_sign":18,"minecraft:sea_pickle":12,"minecraft:activator_rail":6,"minecraft:red_sand":3,"minecraft:gold_nugget":194,"minecraft:cobbled_deepslate":311,"minecraft:bucket":3,"minecraft:azalea":1,"minecraft:wooden_shovel":1,"minecraft:iron_pickaxe":2,"minecraft:furnace":1,"minecraft:golden_helmet":1,"minecraft:stick":297,"croptopia:cucumber":2,"minecraft:brown_terracotta":6,"minecraft:oak_fence":6,"minecraft:torch":144,"croptopia:honeydew_seed":6,"minecraft:porkchop":1,"croptopia:olive_seed":2,"minecraft:pointed_dripstone":25,"minecraft:diorite":130,"croptopia:coffee_seed":2,"minecraft:rabbit_foot":2,"minecraft:orange_bed":12,"minecraft:stone_sword":5,"minecraft:cactus":11,"minecraft:light_gray_bed":18,"minecraft:rotten_flesh":54,"minecraft:white_terracotta":13,"minecraft:obsidian":24,"croptopia:garlic_seed":5,"minecraft:cobblestone":491,"minecraft:feather":2,"minecraft:magma_cream":1,"croptopia:broccoli_seed":1,"minecraft:andesite":53,"minecraft:smoker":1,"mcwfences:oak_picket_fence":1,"minecraft:flint":2,"minecraft:tuff":19,"croptopia:blueberry_seed":4,"minecraft:lapis_lazuli":334,"minecraft:dirt":671,"croptopia:toast_with_jam":1,"croptopia:eggplant":2,"croptopia:kiwi_seed":1,"minecraft:bone":31,"croptopia:corn":87,"minecraft:bow":6,"minecraft:wheat_seeds":32,"minecraft:raw_gold":159,"minecraft:rabbit":16,"minecraft:glowstone_dust":88,"minecraft:powered_rail":2,"minecraft:oak_planks":298,"croptopia:sushi":2,"croptopia:chile_pepper_seed":48,"croptopia:dragonfruit":6,"croptopia:tuna":1,"croptopia:mustard":1,"croptopia:rice":48,"minecraft:sand":81,"croptopia:oat":1,"croptopia:eggplant_seed":4,"minecraft:ink_sac":2,"croptopia:coffee_beans":2,"minecraft:dark_oak_log":10,"minecraft:red_terracotta":11,"croptopia:chile_pepper":31,"mcwfences:oak_stockade_fence":1,"minecraft:light_gray_terracotta":8,"mcwfences:oak_pyramid_gate":7,"minecraft:diamond":12,"minecraft:lever":1,"croptopia:pineapple_seed":12,"minecraft:crossbow":1,"minecraft:granite":42,"croptopia:onion_seed":5,"minecraft:golden_apple":12,"minecraft:oak_sapling":57,"minecraft:netherrack":550,"minecraft:dark_oak_fence":29,"croptopia:greenonion":9,"croptopia:toast":3,"minecraft:charcoal":12,"minecraft:crafting_table":5,"minecraft:azure_bluet":1,"minecraft:chicken":1,"minecraft:ladder":59,"minecraft:clay_ball":76,"minecraft:chest_minecart":9,"croptopia:onion":3,"minecraft:gold_block":2,"minecraft:chain":3,"minecraft:shield":3,"croptopia:saguaro_seed":3,"mcwroofs:oak_planks_top_roof":7,"minecraft:compass":1,"croptopia:soybean":28,"mcwroofs:oak_planks_roof":10,"croptopia:tomatillo":2,"croptopia:tomato_seed":1,"minecraft:beef":4,"minecraft:oak_boat":3,"foodtxf:cooked_fish_on_stick":4,"croptopia:pepper_seed":2,"travelersbackpack:black_sleeping_bag":1,"minecraft:light_gray_wool":2,"minecraft:sugar_cane":124,"minecraft:chest":18,"minecraft:egg":17,"minecraft:raw_iron":232,"croptopia:corn_seed":134,"minecraft:oak_door":7,"croptopia:soybean_seed":47,"minecraft:copper_ingot":15,"minecraft:bowl":7,"croptopia:rhubarb_seed":1,"croptopia:knife":1,"minecraft:redstone":285,"minecraft:dark_oak_planks":75,"croptopia:food_press":1,"minecraft:arrow":46,"minecraft:beetroot_seeds":6,"minecraft:shears":3,"minecraft:hay_block":19,"croptopia:rhubarb":1,"minecraft:yellow_terracotta":13,"minecraft:saddle":1,"minecraft:gold_ingot":8,"croptopia:pepper":2,"croptopia:salt":38,"minecraft:glow_berries":11,"minecraft:mutton":5,"minecraft:oxeye_daisy":1,"minecraft:white_wool":5,"minecraft:rail":393,"minecraft:basalt":5,"minecraft:salmon":1,"minecraft:leather":4,"croptopia:greenonion_seed":14,"minecraft:red_mushroom":2,"minecraft:filled_map":1,"croptopia:basil_seed":9,"minecraft:oak_log":221,"minecraft:gunpowder":7,"minecraft:cobblestone_stairs":2,"minecraft:wooden_hoe":1,"minecraft:white_banner":21,"minecraft:orange_terracotta":7,"croptopia:rice_seed":76,"croptopia:garlic":3,"croptopia:olive":1,"croptopia:mortar_and_pestle":1,"minecraft:apple":7,"croptopia:candy_corn":4,"minecraft:rabbit_hide":6,"minecraft:iron_ingot":39,"croptopia:pineapple":4,"minecraft:stone_pickaxe":12,"minecraft:cobweb":28,"minecraft:glass_bottle":2,"croptopia:turnip_seed":4,"croptopia:kiwi":1,"croptopia:honeydew":3,"minecraft:oak_slab":50,"mcwroofs:oak_planks_upper_lower_roof":95,"minecraft:pumpkin":6,"minecraft:quartz":79,"croptopia:cucumber_seed":3,"minecraft:dripstone_block":14,"minecraft:gravel":2,"croptopia:basil":6,"minecraft:white_bed":1,"croptopia:turnip":2,"minecraft:spider_eye":7,"travelersbackpack:standard":10,"mcwroofs:oak_planks_upper_steep_roof":3,"croptopia:lemon":5,"minecraft:pumpkin_seeds":3,"croptopia:saguaro":2,"croptopia:oat_seed":2,"minecraft:stone_axe":6,"croptopia:cooking_pot":1,"croptopia:frying_pan":1,"minecraft:terracotta":80,"minecraft:baked_potato":1,"minecraft:melon_seeds":7,"minecraft:coal":207},"minecraft:crafted":{"croptopia:grape_jam":3,"minecraft:black_dye":10,"ygm76:yg1":1,"minecraft:smooth_stone":3,"minecraft:oak_planks":1424,"minecraft:oak_sign":33,"minecraft:barrel":7,"ygm76:sakai_gun":1,"minecraft:leather_horse_armor":1,"minecraft:cooked_chicken":1,"travelersbackpack:hose_nozzle":1,"minecraft:loom":1,"minecraft:stone":11,"minecraft:cobblestone_stairs":36,"minecraft:lever":1,"minecraft:nether_brick":29,"minecraft:flower_banner_pattern":1,"minecraft:iron_bars":16,"mcwroofs:oak_planks_upper_steep_roof":12,"mcwbridges:pliers":1,"minecraft:dark_oak_door":6,"minecraft:quartz_block":1,"minecraft:glass":81,"minecraft:hopper":1,"mcwroofs:oak_planks_top_roof":30,"minecraft:bow":3,"minecraft:iron_boots":1,"mcwroofs:oak_planks_roof":120,"croptopia:flour":46,"minecraft:chest":22,"mcwroofs:oak_planks_upper_lower_roof":57,"croptopia:salt":9,"croptopia:butter":4,"mcwfences:oak_pyramid_gate":4,"minecraft:stone_hoe":1,"minecraft:smoker":2,"minecraft:glass_bottle":36,"minecraft:oak_slab":42,"minecraft:wooden_shovel":2,"minecraft:crafting_table":6,"minecraft:iron_helmet":1,"minecraft:wooden_pickaxe":2,"travelersbackpack:standard":1,"croptopia:corn_seed":3,"croptopia:soybean_seed":4,"minecraft:clock":1,"mcwroofs:roofing_hammer":1,"minecraft:gold_block":10,"minecraft:hay_block":7,"minecraft:campfire":1,"croptopia:tofu":24,"croptopia:blueberry_jam":13,"minecraft:dark_oak_slab":12,"minecraft:iron_chestplate":1,"minecraft:book":1,"minecraft:paper":21,"minecraft:charcoal":35,"minecraft:diamond_pickaxe":2,"croptopia:molasses":13,"minecraft:shield":6,"croptopia:soy_milk":1,"minecraft:stick":564,"minecraft:stone_slab":6,"minecraft:iron_ingot":133,"minecraft:compass":1,"minecraft:iron_pickaxe":3,"minecraft:stone_sword":6,"minecraft:gold_ingot":120,"minecraft:light_gray_dye":1,"croptopia:knife":1,"minecraft:composter":1,"croptopia:chile_pepper_seed":2,"minecraft:shears":1,"croptopia:strawberry_jam":1,"croptopia:apple_sapling":2,"minecraft:wooden_sword":1,"minecraft:oak_door":9,"croptopia:pizza":1,"minecraft:stone_shovel":3,"croptopia:cooking_pot":1,"minecraft:iron_nugget":9,"minecraft:furnace":9,"minecraft:blast_furnace":1,"minecraft:piston":2,"croptopia:sushi":10,"croptopia:bacon":1,"minecraft:flint_and_steel":1,"minecraft:terracotta":8,"minecraft:black_terracotta":32,"mcwfences:oak_stockade_fence":12,"minecraft:ladder":114,"minecraft:stone_pickaxe":11,"minecraft:cobblestone_wall":6,"croptopia:dough":38,"minecraft:dark_oak_planks":28,"minecraft:golden_helmet":1,"croptopia:frying_pan":1,"minecraft:wheat":90,"croptopia:paprika":14,"minecraft:sugar":111,"croptopia:cinnamon_wood":5,"croptopia:food_press":1,"croptopia:starfruit_sapling":1,"minecraft:enchanting_table":1,"travelersbackpack:backpack_tank":2,"mcwfences:oak_picket_fence":18,"croptopia:water_bottle":112,"minecraft:bowl":8,"minecraft:nether_bricks":6,"croptopia:milk_bottle":48,"croptopia:mortar_and_pestle":1,"croptopia:pumpkin_spice_latte":8,"travelersbackpack:black_sleeping_bag":2,"minecraft:bucket":3,"minecraft:stone_axe":3,"minecraft:bread":9,"croptopia:candy_corn":39,"croptopia:rice_seed":6,"croptopia:rum":2,"minecraft:oak_boat":1,"mcwroofs:oak_planks_steep_roof":24,"mcwdoors:print_oak":8,"croptopia:coffee":12,"croptopia:tofu_and_dumplings":23,"croptopia:cheese":4,"ygm76:bullet":16,"minecraft:oak_stairs":20,"minecraft:wooden_axe":3,"croptopia:pineapple_juice":3,"minecraft:iron_leggings":1,"minecraft:torch":348,"minecraft:clay":16},"minecraft:used":{"ygm76:sakai_gun":2,"minecraft:oak_sign":40,"minecraft:ladder":95,"minecraft:chest":40,"minecraft:shield":343,"minecraft:white_terracotta":11,"mcwroofs:oak_planks_steep_roof":12,"minecraft:obsidian":20,"minecraft:lava_bucket":26,"minecraft:bow":39,"minecraft:hay_block":16,"minecraft:furnace":7,"minecraft:egg":7,"croptopia:rum":4,"minecraft:diorite":2,"croptopia:tomatillo_seed":4,"minecraft:stone_pickaxe":1954,"minecraft:oak_planks":677,"minecraft:cactus":11,"croptopia:pumpkin_spice_latte":2,"minecraft:wooden_pickaxe":137,"minecraft:sugar_cane":17,"minecraft:composter":1,"minecraft:golden_apple":1,"minecraft:glow_berries":3,"minecraft:loom":1,"minecraft:blast_furnace":1,"minecraft:light_gray_terracotta":5,"mcwroofs:oak_planks_upper_lower_roof":76,"minecraft:shears":16,"minecraft:lever":1,"croptopia:greenonion_seed":11,"mcwfences:oak_stockade_fence":10,"minecraft:red_terracotta":1,"croptopia:spinach":1,"croptopia:tomatillo":1,"mcwfences:oak_pyramid_gate":8,"croptopia:sushi":10,"croptopia:toast":3,"minecraft:wooden_sword":26,"mcwroofs:oak_planks_upper_steep_roof":15,"minecraft:andesite":9,"minecraft:chest_minecart":6,"minecraft:oak_boat":1,"mcwfences:oak_picket_fence":19,"minecraft:cobweb":2,"minecraft:stone_sword":557,"minecraft:flint_and_steel":2,"croptopia:cinnamon_wood":6,"minecraft:stone_shovel":314,"croptopia:toast_with_jam":5,"travelersbackpack:black_sleeping_bag":1,"minecraft:stone_hoe":54,"minecraft:wooden_shovel":118,"travelersbackpack:bat":18,"croptopia:pineapple_juice":6,"minecraft:cooked_chicken":5,"minecraft:netherrack":333,"minecraft:orange_bed":12,"minecraft:oak_door":9,"minecraft:torch":353,"minecraft:dirt":178,"mcwroofs:oak_planks_top_roof":36,"croptopia:starfruit_sapling":1,"croptopia:raspberry":1,"minecraft:granite":29,"croptopia:pizza":1,"minecraft:brown_terracotta":1,"minecraft:wooden_axe":180,"minecraft:oak_stairs":19,"minecraft:barrel":7,"croptopia:tofu_and_dumplings":1,"croptopia:candy_corn":38,"minecraft:light_gray_bed":18,"minecraft:cobbled_deepslate":141,"minecraft:orange_terracotta":7,"minecraft:enchanted_golden_apple":1,"minecraft:wheat_seeds":4,"minecraft:cooked_mutton":1,"minecraft:water_bucket":16,"mcwroofs:oak_planks_roof":128,"minecraft:cobblestone_stairs":21,"croptopia:lemon":7,"minecraft:glass_bottle":6,"croptopia:rice_seed":24,"minecraft:baked_potato":1,"croptopia:corn_seed":20,"minecraft:rail":10,"minecraft:terracotta":73,"croptopia:apple_sapling":2,"minecraft:crafting_table":12,"minecraft:oak_slab":40,"croptopia:soybean_seed":10,"minecraft:campfire":1,"minecraft:dark_oak_door":1,"minecraft:smoker":3,"minecraft:oak_log":129,"minecraft:wooden_hoe":136,"minecraft:diamond_pickaxe":24,"minecraft:apple":7,"minecraft:iron_pickaxe":714,"croptopia:chile_pepper_seed":7,"minecraft:stone_axe":285,"minecraft:fishing_rod":13,"travelersbackpack:standard":37,"minecraft:cobblestone":182,"minecraft:white_banner":13,"minecraft:cooked_porkchop":3,"minecraft:bucket":52,"minecraft:pumpkin_pie":10,"minecraft:sea_pickle":3},"minecraft:killed_by":{"minecraft:creeper":3,"minecraft:cave_spider":1,"minecraft:blaze":1,"minecraft:skeleton":1},"minecraft:killed":{"minecraft:cave_spider":5,"minecraft:spider":11,"minecraft:skeleton":26,"minecraft:magma_cube":4,"minecraft:piglin":1,"minecraft:pig":1,"minecraft:creeper":7,"minecraft:pillager":25,"minecraft:zombie":46,"minecraft:ghast":2,"minecraft:cow":2,"minecraft:rabbit":15,"minecraft:wither_skeleton":1},"minecraft:mined":{"minecraft:dark_oak_planks":72,"croptopia:pepper_crop":1,"minecraft:farmland":3,"minecraft:cobblestone_stairs":2,"minecraft:obsidian":24,"croptopia:cinnamon_wood":1,"minecraft:granite":34,"minecraft:red_sand":3,"minecraft:grass_block":406,"minecraft:light_gray_bed":18,"minecraft:oak_wall_sign":17,"minecraft:oxeye_daisy":1,"croptopia:honeydew_crop":3,"minecraft:spawner":2,"mcwroofs:oak_planks_top_roof":7,"minecraft:tall_seagrass":1,"minecraft:glowstone":28,"minecraft:iron_ore":107,"minecraft:fire":71,"minecraft:cobbled_deepslate":13,"minecraft:pumpkin":6,"mcwfences:oak_picket_fence":1,"minecraft:deepslate_lapis_ore":35,"minecraft:azure_bluet":1,"minecraft:pointed_dripstone":17,"minecraft:oak_sign":1,"minecraft:dirt_path":1,"minecraft:oak_stairs":1,"mcwroofs:oak_planks_upper_steep_roof":3,"travelersbackpack:black_sleeping_bag":2,"minecraft:white_banner":7,"minecraft:orange_bed":12,"mcwfences:oak_pyramid_gate":7,"minecraft:deepslate_redstone_ore":42,"croptopia:eggplant_crop":2,"minecraft:smoker":1,"minecraft:orange_terracotta":7,"minecraft:clay":19,"croptopia:turnip_crop":2,"minecraft:torch":3,"minecraft:light_gray_terracotta":6,"croptopia:oat_crop":1,"croptopia:garlic_crop":3,"minecraft:chest":9,"minecraft:dead_bush":35,"minecraft:nether_quartz_ore":79,"minecraft:cobblestone":20,"croptopia:broccoli_crop":1,"minecraft:oak_planks":167,"minecraft:sugar_cane":60,"minecraft:wall_torch":15,"minecraft:white_terracotta":10,"minecraft:chain":5,"croptopia:peanut_crop":1,"mcwroofs:oak_planks_upper_lower_roof":76,"minecraft:birch_log":1,"croptopia:pineapple_crop":3,"minecraft:wheat":7,"croptopia:tomatillo_crop":2,"croptopia:chile_pepper_crop":31,"minecraft:grass":60,"minecraft:oak_log":159,"croptopia:salt_ore":15,"croptopia:rice_crop":48,"minecraft:sand":85,"minecraft:dirt":181,"minecraft:netherrack":587,"croptopia:basil_crop":6,"minecraft:oak_leaves":18,"minecraft:deepslate":239,"minecraft:yellow_terracotta":13,"minecraft:diamond_ore":2,"minecraft:nether_gold_ore":48,"croptopia:cucumber_crop":2,"minecraft:tuff":14,"minecraft:deepslate_diamond_ore":6,"minecraft:oak_door":3,"minecraft:dark_oak_log":10,"croptopia:onion_crop":3,"minecraft:lever":1,"minecraft:dark_oak_fence":22,"croptopia:coffee_crop":3,"minecraft:hay_block":21,"travelersbackpack:bat":2,"minecraft:redstone_ore":9,"minecraft:furnace":1,"croptopia:corn_crop":87,"croptopia:soybean_crop":28,"minecraft:andesite":41,"minecraft:gold_block":2,"minecraft:deepslate_iron_ore":123,"minecraft:vine":1,"minecraft:rail":323,"croptopia:greenonion_crop":9,"minecraft:stone":379,"minecraft:oak_slab":31,"mcwroofs:oak_planks_roof":10,"minecraft:basalt":6,"travelersbackpack:standard":10,"minecraft:oak_fence":2,"minecraft:crafting_table":6,"minecraft:copper_ore":8,"minecraft:lapis_ore":2,"minecraft:deepslate_gold_ore":59,"mcwfences:oak_stockade_fence":1,"minecraft:diorite":75,"croptopia:olive_crop":1,"minecraft:cactus":7,"minecraft:red_terracotta":11,"minecraft:sea_pickle":4,"minecraft:white_wall_banner":2,"croptopia:dragonfruit_crop":6,"minecraft:coal_ore":168,"croptopia:saguaro_crop":2,"croptopia:kiwi_crop":1,"minecraft:gravel":2,"minecraft:dripstone_block":15,"minecraft:brown_terracotta":5,"minecraft:cobweb":19,"minecraft:terracotta":80,"minecraft:gold_ore":101,"minecraft:fern":8}},"DataVersion":3337}